skill_spelling/LICENSE
skill_spelling/LICENSE.md
skill_spelling/README.md
skill_spelling/__init__.py
skill_spelling/skill.json
skill_spelling/version.py
skill_spelling/neon_skill_spelling.egg-info/PKG-INFO
skill_spelling/neon_skill_spelling.egg-info/SOURCES.txt
skill_spelling/neon_skill_spelling.egg-info/dependency_links.txt
skill_spelling/neon_skill_spelling.egg-info/entry_points.txt
skill_spelling/neon_skill_spelling.egg-info/requires.txt
skill_spelling/neon_skill_spelling.egg-info/top_level.txt
skill_spelling/regex/ca-es/word.rx
skill_spelling/regex/da-dk/word.rx
skill_spelling/regex/de-de/word.rx
skill_spelling/regex/el-gr/word.rx
skill_spelling/regex/en-us/word.rx
skill_spelling/regex/es-es/word.rx
skill_spelling/regex/fa-ir/word.rx
skill_spelling/regex/fr-fr/word.rx
skill_spelling/regex/gl-es/word.rx
skill_spelling/regex/hu-hu/word.rx
skill_spelling/regex/it-it/word.rx
skill_spelling/regex/nl-nl/word.rx
skill_spelling/regex/pl-pl/word.rx
skill_spelling/regex/pt-br/word.rx
skill_spelling/regex/ro-ro/word.rx
skill_spelling/regex/ru-ru/word.rx
skill_spelling/regex/sv-se/word.rx
skill_spelling/regex/tr-tr/word.rx
skill_spelling/vocab/ca-es/Spell.voc
skill_spelling/vocab/da-dk/Spell.voc
skill_spelling/vocab/de-de/Spell.voc
skill_spelling/vocab/el-gr/Spell.voc
skill_spelling/vocab/en-us/Spell.voc
skill_spelling/vocab/es-es/Spell.voc
skill_spelling/vocab/fa-ir/Spell.voc
skill_spelling/vocab/fr-fr/Spell.voc
skill_spelling/vocab/gl-es/Spell.voc
skill_spelling/vocab/hu-hu/Spell.voc
skill_spelling/vocab/it-it/Spell.voc
skill_spelling/vocab/nl-nl/Spell.voc
skill_spelling/vocab/pl-pl/Spell.voc
skill_spelling/vocab/pt-br/Spell.voc
skill_spelling/vocab/ro-ro/Spell.voc
skill_spelling/vocab/ru-ru/Spell.voc
skill_spelling/vocab/sv-se/Spell.voc
skill_spelling/vocab/tr-tr/Spell.voc
neon_skill_spelling-1.1.1.dist-info/LICENSE
neon_skill_spelling-1.1.1.dist-info/LICENSE.md
neon_skill_spelling-1.1.1.dist-info/METADATA
neon_skill_spelling-1.1.1.dist-info/WHEEL
neon_skill_spelling-1.1.1.dist-info/entry_points.txt
neon_skill_spelling-1.1.1.dist-info/top_level.txt
neon_skill_spelling-1.1.1.dist-info/RECORD
